pm4pybenchmark/__init__.py
pm4pybenchmark-0.1.2.dist-info/LICENSE
pm4pybenchmark-0.1.2.dist-info/METADATA
pm4pybenchmark-0.1.2.dist-info/WHEEL
pm4pybenchmark-0.1.2.dist-info/top_level.txt
pm4pybenchmark-0.1.2.dist-info/RECORD
