Metadata-Version: 2.1
Name: pm4pybenchmark
Version: 0.1.2
Summary: Process Mining for Python - Benchmark
Home-page: http://www.pm4py.org
Author: Alessandro Berti
Author-email: alessandro.berti89@gmail.com
License: GPL 3.0
Project-URL: Documentation, http://pm4py.pads.rwth-aachen.de/documentation/
Project-URL: Source, https://github.com/pm4py/pm4py-source
Project-URL: Tracker, https://github.com/pm4py/pm4py-source/issues
Platform: UNKNOWN
Requires-Dist: pm4py (>=1.3.1)
Requires-Dist: requests
